[
    {
    "articulo": "Macbook",
    "codigo": 678990,
    "foto": "./images/macbook.png",
    "descripcion": "Macbook 16 pulgadas, 128 gb, velocidad 16 mb ",
    "colores": "black, silver, gold, gold rose",
    "precio": 2090,
    "id": 1,
    "stock": 24
    },
    {
    "articulo": "Ipad",
    "codigo": 113498,
    "foto": "./images/tablet.png",
    "descripcion": "Ipad 8 pulgadas, 64 gb, velocidad 12 mb, resolución 8px",
    "colores": "black, silver, gold, gold rose",
    "precio": 989,
    "id": 2,
    "stock": 31
    },
    {
    "articulo": "Watch",
    "codigo": 7789553,
    
    "foto": "./images/watch.png",
    "descripcion": "Watch 2 pulgadas, 8 gb, velocidad 8 mb",
    "colores":  "black, silver, gold, gold rose",
    "precio": 1700,
    "id": 3,
    "stock": 24
    },
    {
    "articulo": "Iphone",
    "codigo": 111209,
    "foto": "./images/iphone.png",
    "descripcion": "I phone 14 pro 8 pulgadas, 8 gb, velocidad 8 mb",
    "colores":  "black, silver, gold, gold rose",
    "precio": 1450,
    "id": 4,
    "stock": 13
    },
    {
    "articulo": "Macbook",
    "codigo": 338977,
    "foto": "./images/macbook.png",
    "descripcion": "Macbook 16 pulgadas, 128 gb, velocidad 16 mb",
    "colores":  "black, silver, gold, gold rose",
    "precio": 2090,
    "id": 5,
    "stock": 62
    },
    {
    "articulo": "Ipad",
    "codigo": 223667,
    "foto": "./images/tablet.png",
    "descripcion": "Ipad 8 pulgadas, 64 gb, velocidad 12 mb, resolución 8px",
    "colores": "black, silver, gold, gold rose",
    "precio": 989,
    "id": 6,
    "stock": 25
    }
    ]